s3fs/__init__.py
s3fs/_version.py
s3fs/core.py
s3fs/errors.py
s3fs/mapping.py
s3fs/utils.py
s3fsminio-1.0.0.dist-info/LICENSE.txt
s3fsminio-1.0.0.dist-info/METADATA
s3fsminio-1.0.0.dist-info/WHEEL
s3fsminio-1.0.0.dist-info/top_level.txt
s3fsminio-1.0.0.dist-info/RECORD
