Metadata-Version: 2.1
Name: s3fsminio
Version: 1.0.0
Summary: Convenient Filesystem interface over S3
Home-page: http://github.com/dpulpeiro/s3fsminio/
Maintainer: Daniel Garcia Pulpeiro
Maintainer-email: danielgarciapulpeiro@gmail.com
License: BSD
Keywords: s3,boto
Platform: UNKNOWN
Classifier: Development Status :: 4 - Beta
Classifier: Intended Audience :: Developers
Classifier: License :: OSI Approved :: BSD License
Classifier: Operating System :: OS Independent
Classifier: Programming Language :: Python :: 3.6
Classifier: Programming Language :: Python :: 3.7
Classifier: Programming Language :: Python :: 3.8
Classifier: Programming Language :: Python :: 3.9
Requires-Python: >= 3.6
License-File: LICENSE.txt
Requires-Dist: aiobotocore (~=1.4.1)
Requires-Dist: fsspec (==2021.11.0)
Requires-Dist: aiohttp (>=3.7.1)
Provides-Extra: awscli
Requires-Dist: aiobotocore[awscli] (~=1.4.1) ; extra == 'awscli'
Provides-Extra: boto3
Requires-Dist: aiobotocore[boto3] (~=1.4.1) ; extra == 'boto3'
